{
  "meta": {
    "id": "cf83e1357eefb8bdf1542850d66d8007d620e4050b5715dc83f4a921d36ce9ce47d0d13c5d85f2b0ff8318d2877eec2f63b931bd47417a81a538327af927da3e",
    "parentId": null,
    "name": "Order workflow 1",
    "description": "Simple order workflow",
    "changedOn": "1495118748919",
    "changedBy": "admin"
  },
  "data": {
    "initialState": "new",
    "finalStates": [],
    "objectStateFieldName": "status",
    "transitionStarted": null,
    "states": {
      "new": {
        "name": "New",
        "description": "New order created",
        "visual": {
          "bgColor": "#0277bd",
          "textColor": "#fff",
          "points": [300, 300]
        }
      },
      "onHold": {
        "name": "On hold",
        "description": "Order is on hold",
        "visual": {
          "bgColor": "#0277bd",
          "textColor": "#fff",
          "points": [300, 600]
        }
      },
      "canceled": {
        "name": "Canceled",
        "description": "Order has been canceled",
        "visual": {
          "bgColor": "#0277bd",
          "textColor": "#fff",
          "points": [100, 600]
        }
      },
      "pendingPayment": {
        "name": "Pending payment",
        "description": "Pending payment",
        "visual": {
          "bgColor": "#0277bd",
          "textColor": "#fff",
          "points": [300, 900]
        }
      },
      "refunded": {
        "name": "Refunded",
        "description": "Refunded",
        "visual": {
          "bgColor": "#b71c1c",
          "textColor": "#fff",
          "points": [600, 900]
        }
      },
      "complete": {
        "name": "Complete",
        "description": "Order complete",
        "visual": {
          "bgColor": "#0277bd",
          "textColor": "#fff",
          "points": [600, 1200]
        }
      },
      "closed": {
        "name": "Closed",
        "description": "Order closed",
        "visual": {
          "bgColor": "#0277bd",
          "textColor": "#fff",
          "points": [600, 1500]
        }
      },
      "archived": {
        "name": "Archived",
        "description": "Order archived",
        "visual": {
          "bgColor": "#0277bd",
          "textColor": "#fff",
          "points": [600, 1800]
        }
      }
    },
    "transitions": {
      "transition1": {
        "name": "Transition 1",
        "description": "Transition 1 description",
        "from": "new",
        "to": "onHold",
        "options": {
          "properties": {

          },
          "triggers": {

          },
          "conditions": {

          },
          "validators": {

          },
          "postFunctions": {

          }
        },
        "visual": {
          "points": [20,20, 20,100, 40,100, 100,40]
        }
      }
    }
  }
}
